{
  "page": 38,
  "png_size_kb": 392.9,
  "has_text_layer": true,
  "text_char_count": 1440,
  "text_preview": "Savings Account\nPage  \n  of  \n38\n38\nDate\nTransaction Id\nRemarks\nAmount( )\nBalance( )\n21-04-2026\nY36982063\nUPIAB/290095027980/CR/ROUTHU /SBIN/routhujanardha\n1000.0(Cr)\n138788.88(Cr)\n21-04-2026\nY66328299\nUPIAR/349445966912/DR/ PhonePe/YESB/SV251211223834\n920.0(Dr)\n137868.88(Cr)\n21-04-2026\nY66336109\nUPIAB/854479354841/CR/KUSUMAPU/BARB/korada30112@yb\n20000.0(Cr)\n157868.88(Cr)\n21-04-2026\nY66816219\nUPIAR/503131001081/DR/Bank Acc/SBIN/62214014329@SB\n20000.0(Dr)\n137868.88(Cr)\n21-04-2026\nY66918270\nUPIAR/"
}